<?xml version='1.0' encoding='UTF-8' ?>
<competiciones
    xmlns:xs="http://www.w3.org/2001/XMLSchema-instance" 
    xs:noNamespaceSchemaLocation="resultados_ultima_jornada.xsd"
>
    <competicion id_competicion="1">
        <nombre_competicion>torneo 1</nombre_competicion>
        <jornada id_jornada="3" Fecha="2024-03-15">
            <numero_jornada>3</numero_jornada>
            <enfrentamiento id="5">
                <cod_equipo_local>1</cod_equipo_local>
                <cod_equipo_visitante>4</cod_equipo_visitante>
                <ganador>Team Alpha</ganador>
            </enfrentamiento>
            <enfrentamiento id="6">
                <cod_equipo_local>2</cod_equipo_local>
                <cod_equipo_visitante>3</cod_equipo_visitante>
                <ganador>Team Bravo</ganador>
            </enfrentamiento>
        </jornada>
    </competicion>
    <competicion id_competicion="2">
        <nombre_competicion>torneo 2</nombre_competicion>
        <jornada id_jornada="6" Fecha="2024-03-15">
            <numero_jornada>3</numero_jornada>
            <enfrentamiento id="11">
                <cod_equipo_local>5</cod_equipo_local>
                <cod_equipo_visitante>8</cod_equipo_visitante>
                <ganador>Team Echo</ganador>
            </enfrentamiento>
            <enfrentamiento id="12">
                <cod_equipo_local>6</cod_equipo_local>
                <cod_equipo_visitante>7</cod_equipo_visitante>
                <ganador>Team Foxtrot</ganador>
            </enfrentamiento>
        </jornada>
    </competicion>
    <competicion id_competicion="3">
        <nombre_competicion>torneo 3</nombre_competicion>
        <jornada id_jornada="9" Fecha="2024-03-15">
            <numero_jornada>3</numero_jornada>
            <enfrentamiento id="15">
                <cod_equipo_local>11</cod_equipo_local>
                <cod_equipo_visitante>12</cod_equipo_visitante>
                <ganador>Team Krack</ganador>
            </enfrentamiento>
        </jornada>
    </competicion>
    <competicion id_competicion="4">
        <nombre_competicion>torneo 4</nombre_competicion>
        <jornada id_jornada="12" Fecha="2024-03-15">
            <numero_jornada>3</numero_jornada>
            <enfrentamiento id="17">
                <cod_equipo_local>1</cod_equipo_local>
                <cod_equipo_visitante>2</cod_equipo_visitante>
                <ganador>Team Alpha</ganador>
            </enfrentamiento>
            <enfrentamiento id="18">
                <cod_equipo_local>3</cod_equipo_local>
                <cod_equipo_visitante>4</cod_equipo_visitante>
                <ganador>Team Charlie</ganador>
            </enfrentamiento>
            <enfrentamiento id="19">
                <cod_equipo_local>5</cod_equipo_local>
                <cod_equipo_visitante>6</cod_equipo_visitante>
                <ganador>Team Echo</ganador>
            </enfrentamiento>
        </jornada>
    </competicion>
</competiciones>
